pyktlib/__init__.py
pyktlib/model/__init__.py
pyktlib/model/module/EmbedLayer.py
pyktlib/model/module/__init__.py
pyktlib/model/sequential_kt/__init__.py
pyktlib-0.1.2.dist-info/LICENSE
pyktlib-0.1.2.dist-info/METADATA
pyktlib-0.1.2.dist-info/WHEEL
pyktlib-0.1.2.dist-info/top_level.txt
pyktlib-0.1.2.dist-info/RECORD
